zempy/__init__.py
zempy/py.typed
zempy/bridge/__init__.py
zempy/bridge/standalone.py
zempy/bridge/zemax_exceptions.py
zempy/bridge/zemax_file_session.py
zempy/bridge/zemax_reg.py
zempy/bridge/zempy_session.py
zempy/dll/dlls.py
zempy/dll/load_dll.py
zempy/dotnet/clr.py
zempy/dotnet/dot_net.py
zempy/dotnet/runtime.py
zempy/zosapi/__init__.py
zempy/zosapi/analysis/__init__.py
zempy/zosapi/analysis/registered.py
zempy/zosapi/analysis/adapters/analyses.py
zempy/zosapi/analysis/adapters/analysis_registry.py
zempy/zosapi/analysis/adapters/ia.py
zempy/zosapi/analysis/adapters/message.py
zempy/zosapi/analysis/adapters/messages.py
zempy/zosapi/analysis/data/adapters/critical_ray_data.py
zempy/zosapi/analysis/data/adapters/critical_ray_info.py
zempy/zosapi/analysis/data/adapters/data_grid.py
zempy/zosapi/analysis/data/adapters/data_series.py
zempy/zosapi/analysis/data/adapters/header_data.py
zempy/zosapi/analysis/data/adapters/meta_data.py
zempy/zosapi/analysis/data/adapters/nsc_single_ray_trace_data.py
zempy/zosapi/analysis/data/adapters/path_analysis_data.py
zempy/zosapi/analysis/data/adapters/path_analysis_entry.py
zempy/zosapi/analysis/data/adapters/ray_data.py
zempy/zosapi/analysis/data/adapters/ray_info.py
zempy/zosapi/analysis/data/adapters/spot_data_result_matrix.py
zempy/zosapi/analysis/data/protocols/i_color_translator.py
zempy/zosapi/analysis/data/protocols/iar_critical_ray_data.py
zempy/zosapi/analysis/data/protocols/iar_critical_ray_info.py
zempy/zosapi/analysis/data/protocols/iar_data_grid.py
zempy/zosapi/analysis/data/protocols/iar_data_grid_rgb.py
zempy/zosapi/analysis/data/protocols/iar_data_scatter_points.py
zempy/zosapi/analysis/data/protocols/iar_data_scatter_points_rgb.py
zempy/zosapi/analysis/data/protocols/iar_data_series.py
zempy/zosapi/analysis/data/protocols/iar_data_series_rgb.py
zempy/zosapi/analysis/data/protocols/iar_header_data.py
zempy/zosapi/analysis/data/protocols/iar_meta_data.py
zempy-0.6.0.dist-info/licenses/LICENSE
zempy-0.6.0.dist-info/METADATA
zempy-0.6.0.dist-info/WHEEL
zempy-0.6.0.dist-info/top_level.txt
zempy-0.6.0.dist-info/RECORD
