Metadata-Version: 2.4
Name: zempy
Version: 0.6.0
Summary: OpticalStudio Python wrapper
Author-email: Anton Sharapov <sharapov.anton@gmail.com>
License-Expression: MIT
Project-URL: Homepage, https://github.com/SharapovAnton/Zempy
Project-URL: Source, https://github.com/SharapovAnton/Zempy
Project-URL: Issues, https://github.com/SharapovAnton/Zempy/issues
Classifier: Programming Language :: Python :: 3
Classifier: Programming Language :: Python :: 3 :: Only
Classifier: Operating System :: OS Independent
Classifier: Topic :: Software Development :: Libraries
Classifier: Typing :: Typed
Requires-Python: >=3.8
License-File: LICENSE
Requires-Dist: numpy>=1.23
Requires-Dist: pythonnet>=3.0.5
Requires-Dist: clr_loader>=0.2.7
Requires-Dist: allytools>=0.6.0
Provides-Extra: dev
Requires-Dist: pytest; extra == "dev"
Requires-Dist: mypy; extra == "dev"
Requires-Dist: ruff; extra == "dev"
Provides-Extra: qa
Requires-Dist: tox; extra == "qa"
Requires-Dist: pre-commit; extra == "qa"
Provides-Extra: gui
Requires-Dist: PyQt5; extra == "gui"
Dynamic: license-file
